LICENSE
README.md
README.rst
setup.py
enka.py.egg-info/PKG-INFO
enka.py.egg-info/SOURCES.txt
enka.py.egg-info/dependency_links.txt
enka.py.egg-info/not-zip-safe
enka.py.egg-info/requires.txt
enka.py.egg-info/top_level.txt
enkapy/__init__.py
enkapy/client.py
enkapy/exception.py
enkapy/model/__init__.py
enkapy/model/artifact.py
enkapy/model/character.py
enkapy/model/combats.py
enkapy/model/players.py
enkapy/model/weapon.py