Metadata-Version: 2.1
Name: enka.py
Version: 1.2.1
Summary: Library for fetching JSON data from site https://enka.network/
Home-page: https://github.com/pwnless/enka.py
Author: pwnless
Author-email: mystream@riseup.net
Keywords: enkapy.py,enkapy,enka.network,genshinapi
Classifier: Programming Language :: Python :: 3
Classifier: License :: OSI Approved :: MIT License
Classifier: Operating System :: OS Independent
Requires-Python: >=3.6
License-File: LICENSE
